setup.py
lie_to_me/__init__.py
lie_to_me/context.py
lie_to_me/extra_assertions.py
lie_to_me.egg-info/PKG-INFO
lie_to_me.egg-info/SOURCES.txt
lie_to_me.egg-info/dependency_links.txt
lie_to_me.egg-info/requires.txt
lie_to_me.egg-info/top_level.txt