Metadata-Version: 1.0
Name: lie-to-me
Version: 0.0.1b
Summary: Lie to me is a mock library to test code using pyVows.
Home-page: http://github.com/rafaelcaricio/lie_to_me/
Author: Rafael Caricio
Author-email: rafael@caricio.com
License: MIT
Keywords: tdd vows testing mock pyvows
Platform: UNKNOWN
Classifier: Development Status :: 3 - Alpha
Classifier: Intended Audience :: Developers
Classifier: License :: OSI Approved :: MIT License
Classifier: Natural Language :: English
Classifier: Operating System :: MacOS
Classifier: Operating System :: Microsoft :: Windows
Classifier: Operating System :: POSIX :: Linux
Classifier: Topic :: Software Development :: Testing
